cenfind/__init__.py
cenfind/__main__.py
cenfind/cli/__init__.py
cenfind/cli/analyse.py
cenfind/cli/score.py
cenfind/cli/train.py
cenfind/cli/vignettes.py
cenfind/constants.py
cenfind/core/__init__.py
cenfind/core/data.py
cenfind/core/detectors.py
cenfind/core/loading.py
cenfind/core/measure.py
cenfind/core/serialise.py
cenfind/core/statistics.py
cenfind/core/structures.py
cenfind/core/visualisation.py
cenfind/publication/__init__.py
cenfind/publication/compare_detectors.py
cenfind/publication/compare_nuclei.py
cenfind/publication/compare_precision_recall.py
cenfind/publication/count_nuclei.py
cenfind/publication/detectors_other.py
cenfind/publication/plot_accuracy.py
cenfind/publication/plot_pr_curve_all_ds.py
cenfind/publication/rescue_fields.py
cenfind/publication/train_all_dataset_unet.py
cenfind/publication/train_with_ablation.py
cenfind/training/__init__.py
cenfind/training/config.py
cenfind/training/download_annotations.py
cenfind/training/evaluate.py
cenfind/training/helpers.py
cenfind/training/predict.py
cenfind/training/upload.py
cenfind/training/upload_labels_mal.py
cenfind-0.15.2.dist-info/entry_points.txt
cenfind-0.15.2.dist-info/WHEEL
cenfind-0.15.2.dist-info/LICENSE
cenfind-0.15.2.dist-info/METADATA
cenfind-0.15.2.dist-info/RECORD
