Metadata-Version: 2.1
Name: cenfind
Version: 0.15.2
Summary: Score cells for centrioles in IF data
Home-page: https://github.com/UPGON/cenfind
License: MIT
Keywords: microscopy,scientific,biology,image-analysis
Author: Leo Burgy
Author-email: leo.burgy@epfl.ch
Requires-Python: >=3.9,<3.11
Classifier: License :: OSI Approved :: MIT License
Classifier: Programming Language :: Python :: 3
Classifier: Programming Language :: Python :: 3.9
Classifier: Programming Language :: Python :: 3.10
Requires-Dist: albumentations (>=1.3.0,<2.0.0)
Requires-Dist: attrs (>=22.2.0,<23.0.0)
Requires-Dist: csbdeep (>=0.7.3,<0.8.0)
Requires-Dist: llvmlite (==0.39.1)
Requires-Dist: numba (==0.56.4)
Requires-Dist: numpy (>=1.23.5,<2.0.0)
Requires-Dist: opencv-python (>=4.7.0.72,<5.0.0.0)
Requires-Dist: ortools (==9.4.1874)
Requires-Dist: pandas (>=1.4.1,<2.0.0)
Requires-Dist: protobuf (==3.19.6)
Requires-Dist: scikit-image (>=0.19.2,<0.20.0)
Requires-Dist: scikit-learn (>=1.2.1,<2.0.0)
Requires-Dist: scipy (>=1.7.1,<2.0.0)
Requires-Dist: seaborn (>=0.13.0,<0.14.0)
Requires-Dist: spotipy-detector (>=0.1.0,<0.2.0)
Requires-Dist: stardist (>=0.8.3,<0.9.0)
Requires-Dist: tensorflow (==2.9.0) ; sys_platform == "win32" or sys_platform == "linux"
Requires-Dist: tensorflow-macos (==2.9.0) ; sys_platform == "darwin"
Requires-Dist: tensorflow-metal (==0.5.0) ; sys_platform == "darwin"
Requires-Dist: tifffile (>=2022.5.4,<2023.0.0)
Requires-Dist: tqdm (>=4.62.3,<5.0.0)
Project-URL: Repository, https://github.com/UPGON/cenfind
